statelit/__init__.py
statelit/core.py
statelit/json.py
statelit/types.py
statelit/field_factory/__init__.py
statelit/field_factory/base.py
statelit/field_factory/main.py
statelit/state/__init__.py
statelit/state/base.py
statelit/state/field.py
statelit/state/model.py
statelit/utils/__init__.py
statelit/utils/misc.py
statelit/utils/mro.py
statelit-0.1.2.dist-info/LICENSE
statelit-0.1.2.dist-info/WHEEL
statelit-0.1.2.dist-info/METADATA
statelit-0.1.2.dist-info/RECORD
