Metadata-Version: 2.1
Name: statelit
Version: 0.1.2
Summary: Easy state management in Streamlit with Pydantic.
Home-page: https://github.com/dwreeves/statelit
License: MIT
Author: Daniel Reeves
Author-email: xdanielreeves@gmail.com
Requires-Python: >=3.7
Classifier: Framework :: Apache Airflow
Classifier: Intended Audience :: Developers
Classifier: License :: OSI Approved :: MIT License
Classifier: Operating System :: OS Independent
Classifier: Programming Language :: Python
Classifier: Programming Language :: Python :: 3
Classifier: Programming Language :: Python :: 3.7
Classifier: Programming Language :: Python :: 3.8
Classifier: Programming Language :: Python :: 3.9
Classifier: Programming Language :: Python :: 3.10
Classifier: Programming Language :: Python :: 3.11
Requires-Dist: streamlit
Requires-Dist: pydantic<2
Requires-Dist: mkdocs ; extra == "doc"
Requires-Dist: pymdown-extensions ; extra == "doc"
Requires-Dist: mkdocs-material ; extra == "doc"
Requires-Dist: mkdocs-macros-plugin ; extra == "doc"
Requires-Dist: pygments ; extra == "doc"
Requires-Dist: markdown-include ; extra == "doc"
Requires-Dist: pre-commit ; extra == "test"
Requires-Dist: pytest ; extra == "test"
Requires-Dist: pytest-cov ; extra == "test"
Requires-Dist: isort ; extra == "test"
Requires-Dist: flake8 ; extra == "test"
Requires-Dist: flakeheaven>3 ; extra == "test"
Requires-Dist: pandas ; extra == "test"
Provides-Extra: doc
Provides-Extra: test
